Metadata-Version: 2.1
Name: hack4u_academy
Version: 0.1.0
Summary: Una biblioteca para consultar cursos en Hack4u.
Home-page: https://hack4u.io
Author: Isabela Gomez
